ironic_importer/__init__.py
ironic_importer/inventory.py
ironic_inventory-0.9.3.data/data/examples/ironic_nodes.xlsx
ironic_inventory-0.9.3.dist-info/LICENSE
ironic_inventory-0.9.3.dist-info/METADATA
ironic_inventory-0.9.3.dist-info/WHEEL
ironic_inventory-0.9.3.dist-info/entry_points.txt
ironic_inventory-0.9.3.dist-info/top_level.txt
ironic_inventory-0.9.3.dist-info/RECORD
